setup.cfg
setup.py
target_magentobi/__init__.py
target_magentobi/buffer.py
target_magentobi/client.py
target_magentobi.egg-info/PKG-INFO
target_magentobi.egg-info/SOURCES.txt
target_magentobi.egg-info/dependency_links.txt
target_magentobi.egg-info/entry_points.txt
target_magentobi.egg-info/requires.txt
target_magentobi.egg-info/top_level.txt