Metadata-Version: 1.1
Name: target-magentobi
Version: 0.1.0
Summary: Singer.io target for the Magento Business Intelligence API
Home-page: http://www.robertjmoore.com/
Author: Robert J. Moore
Author-email: robertj@robertjmoore.com
License: UNKNOWN
Platform: UNKNOWN
Classifier: Programming Language :: Python :: 3 :: Only
